.DS_Store
automate_insurance_pricing/__init__.py
automate_insurance_pricing/standard_functions.py
automate_insurance_pricing/exploration/__init__.py
automate_insurance_pricing/exploration/checks_functions.py
automate_insurance_pricing/preprocessing/__init__.py
automate_insurance_pricing/preprocessing/charts_functions.py
automate_insurance_pricing/preprocessing/create_functions.py
automate_insurance_pricing/preprocessing/descriptive_functions.py
automate_insurance_pricing/preprocessing/encoding_functions.py
automate_insurance_pricing/reports/__init__.py
automate_insurance_pricing/reports/export_functions.py
automate_insurance_pricing/reports/write_notes.py
automate_insurance_pricing/risk_performance/__init__.py
automate_insurance_pricing/risk_performance/analysis_functions.py
automate_insurance_pricing/risk_performance/triangles_functions.py
automate_insurance_pricing/risk_prediction/__init__.py
automate_insurance_pricing/risk_prediction/charts_functions.py
automate_insurance_pricing/risk_prediction/features_selection.py
automate_insurance_pricing/risk_prediction/model_selection.py
automate_insurance_pricing/risk_prediction/predict_functions.py
automate_insurance_pricing-1.0.5.dist-info/LICENCE
automate_insurance_pricing-1.0.5.dist-info/METADATA
automate_insurance_pricing-1.0.5.dist-info/WHEEL
automate_insurance_pricing-1.0.5.dist-info/top_level.txt
automate_insurance_pricing-1.0.5.dist-info/RECORD
