Metadata-Version: 2.1
Name: automate-insurance-pricing
Version: 1.0.5
Summary: Bunch of functions for insurance pricing purposes
Home-page: https://github.com/nassmim/automate-insurance-pricing
Author: Nassim Ezzakraoui
Author-email: nassmim972@gmail.com
License: UNKNOWN
Platform: UNKNOWN
Classifier: Programming Language :: Python
Classifier: License :: OSI Approved :: MIT License
Classifier: Operating System :: OS Independent
Requires-Python: ~=3.7
Requires-Dist: chainladder (~=0.7)
Requires-Dist: hyperopt (~=0.2)
Requires-Dist: joypy (~=0.2)
Requires-Dist: matplotlib (~=3.1)
Requires-Dist: numpy (~=1.18)
Requires-Dist: openpyxl (~=3.0)
Requires-Dist: pandas (~=1.0)
Requires-Dist: scikit-learn (~=0.22)
Requires-Dist: scipy (~=1.4)
Requires-Dist: seaborn (~=0.10)
Requires-Dist: statsmodels (~=0.11)
Requires-Dist: xlrd (~=1.2)
Requires-Dist: XlsxWriter (~=1.2)
Requires-Dist: xlwings (~=0.19)
Requires-Dist: docx-mailmerge (~=0.5)
